{"info":{"file":"lib/util/set.js","fileShort":"lib/util/set.js","fileSafe":"lib_util_set_js","link":"files/lib_util_set_js/index.html"},"complexity":{"methodAggregate":{"cyclomatic":18,"cyclomaticDensity":22.222,"halstead":{"bugs":1.192,"difficulty":58.094,"effort":207801.986,"length":551,"time":11544.555,"vocabulary":90,"volume":3577.011,"operands":{"distinct":64,"total":286,"identifiers":["__stripped__"]},"operators":{"distinct":26,"total":265,"identifiers":["__stripped__"]}},"params":24,"sloc":{"logical":81,"physical":92}},"settings":{"commonjs":true,"forin":false,"logicalor":true,"switchcase":true,"trycatch":false,"newmi":true},"classes":[],"dependencies":[{"line":3,"path":"./typal","type":"cjs"}],"errors":[],"lineEnd":92,"lineStart":1,"maintainability":80.73,"methods":[{"cyclomatic":5,"cyclomaticDensity":71.429,"halstead":{"bugs":0.063,"difficulty":9.409,"effort":1789.278,"length":44,"time":99.404,"vocabulary":20,"volume":190.165,"operands":{"distinct":11,"total":23,"identifiers":["__stripped__"]},"operators":{"distinct":9,"total":21,"identifiers":["__stripped__"]}},"params":2,"sloc":{"logical":7,"physical":7},"errors":[],"lineEnd":12,"lineStart":6,"name":"Set_constructor"},{"cyclomatic":2,"cyclomaticDensity":100,"halstead":{"bugs":0.02,"difficulty":4.4,"effort":265.006,"length":19,"time":14.723,"vocabulary":9,"volume":60.229,"operands":{"distinct":5,"total":11,"identifiers":["__stripped__"]},"operators":{"distinct":4,"total":8,"identifiers":["__stripped__"]}},"params":1,"sloc":{"logical":2,"physical":4},"errors":[],"lineEnd":16,"lineStart":13,"name":"concat"},{"cyclomatic":2,"cyclomaticDensity":200,"halstead":{"bugs":0.021,"difficulty":5,"effort":315.583,"length":19,"time":17.532,"vocabulary":10,"volume":63.117,"operands":{"distinct":5,"total":10,"identifiers":["__stripped__"]},"operators":{"distinct":5,"total":9,"identifiers":["__stripped__"]}},"params":1,"sloc":{"logical":1,"physical":3},"errors":[],"lineEnd":19,"lineStart":17,"name":"eq"},{"cyclomatic":5,"cyclomaticDensity":71.429,"halstead":{"bugs":0.063,"difficulty":13.444,"effort":2556.661,"length":44,"time":142.037,"vocabulary":20,"volume":190.165,"operands":{"distinct":9,"total":22,"identifiers":["__stripped__"]},"operators":{"distinct":11,"total":22,"identifiers":["__stripped__"]}},"params":1,"sloc":{"logical":7,"physical":9},"errors":[],"lineEnd":28,"lineStart":20,"name":"indexOf"},{"cyclomatic":1,"cyclomaticDensity":100,"halstead":{"bugs":0.017,"difficulty":2.667,"effort":132.877,"length":15,"time":7.382,"vocabulary":10,"volume":49.829,"operands":{"distinct":6,"total":8,"identifiers":["__stripped__"]},"operators":{"distinct":4,"total":7,"identifiers":["__stripped__"]}},"params":1,"sloc":{"logical":1,"physical":3},"errors":[],"lineEnd":31,"lineStart":29,"name":"union"},{"cyclomatic":1,"cyclomaticDensity":100,"halstead":{"bugs":0.008,"difficulty":2,"effort":48,"length":8,"time":2.667,"vocabulary":8,"volume":24,"operands":{"distinct":4,"total":4,"identifiers":["__stripped__"]},"operators":{"distinct":4,"total":4,"identifiers":["__stripped__"]}},"params":1,"sloc":{"logical":1,"physical":5},"errors":[],"lineEnd":36,"lineStart":32,"name":"intersection"},{"cyclomatic":1,"cyclomaticDensity":100,"halstead":{"bugs":0.006,"difficulty":2,"effort":36.189,"length":7,"time":2.011,"vocabulary":6,"volume":18.095,"operands":{"distinct":3,"total":4,"identifiers":["__stripped__"]},"operators":{"distinct":3,"total":3,"identifiers":["__stripped__"]}},"params":1,"sloc":{"logical":1,"physical":3},"errors":[],"lineEnd":35,"lineStart":33,"name":"<anonymous>"},{"cyclomatic":1,"cyclomaticDensity":50,"halstead":{"bugs":0.014,"difficulty":3.6,"effort":149.447,"length":12,"time":8.303,"vocabulary":11,"volume":41.513,"operands":{"distinct":5,"total":6,"identifiers":["__stripped__"]},"operators":{"distinct":6,"total":6,"identifiers":["__stripped__"]}},"params":1,"sloc":{"logical":2,"physical":6},"errors":[],"lineEnd":42,"lineStart":37,"name":"complement"},{"cyclomatic":1,"cyclomaticDensity":100,"halstead":{"bugs":0.007,"difficulty":2.667,"effort":59.89,"length":8,"time":3.327,"vocabulary":7,"volume":22.459,"operands":{"distinct":3,"total":4,"identifiers":["__stripped__"]},"operators":{"distinct":4,"total":4,"identifiers":["__stripped__"]}},"params":1,"sloc":{"logical":1,"physical":3},"errors":[],"lineEnd":41,"lineStart":39,"name":"sub_complement"},{"cyclomatic":4,"cyclomaticDensity":80,"halstead":{"bugs":0.05,"difficulty":9.5,"effort":1426.114,"length":36,"time":79.229,"vocabulary":18,"volume":150.117,"operands":{"distinct":9,"total":19,"identifiers":["__stripped__"]},"operators":{"distinct":9,"total":17,"identifiers":["__stripped__"]}},"params":1,"sloc":{"logical":5,"physical":7},"errors":[],"lineEnd":49,"lineStart":43,"name":"subset"},{"cyclomatic":1,"cyclomaticDensity":100,"halstead":{"bugs":0.006,"difficulty":2,"effort":36.189,"length":7,"time":2.011,"vocabulary":6,"volume":18.095,"operands":{"distinct":3,"total":4,"identifiers":["__stripped__"]},"operators":{"distinct":3,"total":3,"identifiers":["__stripped__"]}},"params":1,"sloc":{"logical":1,"physical":3},"errors":[],"lineEnd":52,"lineStart":50,"name":"superset"},{"cyclomatic":1,"cyclomaticDensity":100,"halstead":{"bugs":0.01,"difficulty":2.25,"effort":69.482,"length":11,"time":3.86,"vocabulary":7,"volume":30.881,"operands":{"distinct":4,"total":6,"identifiers":["__stripped__"]},"operators":{"distinct":3,"total":5,"identifiers":["__stripped__"]}},"params":1,"sloc":{"logical":1,"physical":3},"errors":[],"lineEnd":55,"lineStart":53,"name":"joinSet"},{"cyclomatic":1,"cyclomaticDensity":100,"halstead":{"bugs":0.011,"difficulty":3.125,"effort":99.06,"length":10,"time":5.503,"vocabulary":9,"volume":31.699,"operands":{"distinct":4,"total":5,"identifiers":["__stripped__"]},"operators":{"distinct":5,"total":5,"identifiers":["__stripped__"]}},"params":1,"sloc":{"logical":1,"physical":1},"errors":[],"lineEnd":56,"lineStart":56,"name":"contains"},{"cyclomatic":1,"cyclomaticDensity":100,"halstead":{"bugs":0.007,"difficulty":1.25,"effort":25.85,"length":8,"time":1.436,"vocabulary":6,"volume":20.68,"operands":{"distinct":4,"total":5,"identifiers":["__stripped__"]},"operators":{"distinct":2,"total":3,"identifiers":["__stripped__"]}},"params":2,"sloc":{"logical":1,"physical":1},"errors":[],"lineEnd":57,"lineStart":57,"name":"item"},{"cyclomatic":1,"cyclomaticDensity":100,"halstead":{"bugs":0.007,"difficulty":1.25,"effort":25.85,"length":8,"time":1.436,"vocabulary":6,"volume":20.68,"operands":{"distinct":4,"total":5,"identifiers":["__stripped__"]},"operators":{"distinct":2,"total":3,"identifiers":["__stripped__"]}},"params":2,"sloc":{"logical":1,"physical":1},"errors":[],"lineEnd":58,"lineStart":58,"name":"i"},{"cyclomatic":1,"cyclomaticDensity":100,"halstead":{"bugs":0.005,"difficulty":1,"effort":13.932,"length":6,"time":0.774,"vocabulary":5,"volume":13.932,"operands":{"distinct":3,"total":3,"identifiers":["__stripped__"]},"operators":{"distinct":2,"total":3,"identifiers":["__stripped__"]}},"params":0,"sloc":{"logical":1,"physical":1},"errors":[],"lineEnd":59,"lineStart":59,"name":"first"},{"cyclomatic":1,"cyclomaticDensity":100,"halstead":{"bugs":0.011,"difficulty":2.25,"effort":75.799,"length":12,"time":4.211,"vocabulary":7,"volume":33.688,"operands":{"distinct":4,"total":6,"identifiers":["__stripped__"]},"operators":{"distinct":3,"total":6,"identifiers":["__stripped__"]}},"params":0,"sloc":{"logical":1,"physical":1},"errors":[],"lineEnd":60,"lineStart":60,"name":"last"},{"cyclomatic":1,"cyclomaticDensity":100,"halstead":{"bugs":0.005,"difficulty":1,"effort":13.932,"length":6,"time":0.774,"vocabulary":5,"volume":13.932,"operands":{"distinct":3,"total":3,"identifiers":["__stripped__"]},"operators":{"distinct":2,"total":3,"identifiers":["__stripped__"]}},"params":0,"sloc":{"logical":1,"physical":1},"errors":[],"lineEnd":61,"lineStart":61,"name":"size"},{"cyclomatic":1,"cyclomaticDensity":100,"halstead":{"bugs":0.007,"difficulty":1.5,"effort":33.688,"length":8,"time":1.872,"vocabulary":7,"volume":22.459,"operands":{"distinct":4,"total":4,"identifiers":["__stripped__"]},"operators":{"distinct":3,"total":4,"identifiers":["__stripped__"]}},"params":0,"sloc":{"logical":1,"physical":1},"errors":[],"lineEnd":62,"lineStart":62,"name":"isEmpty"},{"cyclomatic":1,"cyclomaticDensity":100,"halstead":{"bugs":0.005,"difficulty":1.5,"effort":23.265,"length":6,"time":1.292,"vocabulary":6,"volume":15.51,"operands":{"distinct":3,"total":3,"identifiers":["__stripped__"]},"operators":{"distinct":3,"total":3,"identifiers":["__stripped__"]}},"params":0,"sloc":{"logical":1,"physical":1},"errors":[],"lineEnd":63,"lineStart":63,"name":"copy"},{"cyclomatic":1,"cyclomaticDensity":100,"halstead":{"bugs":0.006,"difficulty":1.5,"effort":27.142,"length":7,"time":1.508,"vocabulary":6,"volume":18.095,"operands":{"distinct":3,"total":3,"identifiers":["__stripped__"]},"operators":{"distinct":3,"total":4,"identifiers":["__stripped__"]}},"params":0,"sloc":{"logical":1,"physical":1},"errors":[],"lineEnd":64,"lineStart":64,"name":"toString"},{"cyclomatic":1,"cyclomaticDensity":50,"halstead":{"bugs":0.015,"difficulty":2.7,"effort":121.5,"length":15,"time":6.75,"vocabulary":8,"volume":45,"operands":{"distinct":5,"total":9,"identifiers":["__stripped__"]},"operators":{"distinct":3,"total":6,"identifiers":["__stripped__"]}},"params":2,"sloc":{"logical":2,"physical":4},"errors":[],"lineEnd":70,"lineStart":67,"name":"<anonymous>"},{"cyclomatic":1,"cyclomaticDensity":100,"halstead":{"bugs":0.014,"difficulty":1.5,"effort":64.778,"length":13,"time":3.599,"vocabulary":10,"volume":43.185,"operands":{"distinct":7,"total":7,"identifiers":["__stripped__"]},"operators":{"distinct":3,"total":6,"identifiers":["__stripped__"]}},"params":0,"sloc":{"logical":1,"physical":1},"errors":[],"lineEnd":68,"lineStart":68,"name":"<anonymous>"},{"cyclomatic":1,"cyclomaticDensity":50,"halstead":{"bugs":0.015,"difficulty":2.7,"effort":121.5,"length":15,"time":6.75,"vocabulary":8,"volume":45,"operands":{"distinct":5,"total":9,"identifiers":["__stripped__"]},"operators":{"distinct":3,"total":6,"identifiers":["__stripped__"]}},"params":2,"sloc":{"logical":2,"physical":4},"errors":[],"lineEnd":74,"lineStart":71,"name":"<anonymous>"},{"cyclomatic":1,"cyclomaticDensity":100,"halstead":{"bugs":0.02,"difficulty":2,"effort":118.414,"length":16,"time":6.579,"vocabulary":13,"volume":59.207,"operands":{"distinct":9,"total":9,"identifiers":["__stripped__"]},"operators":{"distinct":4,"total":7,"identifiers":["__stripped__"]}},"params":0,"sloc":{"logical":1,"physical":1},"errors":[],"lineEnd":72,"lineStart":72,"name":"<anonymous>"},{"cyclomatic":4,"cyclomaticDensity":44.444,"halstead":{"bugs":0.085,"difficulty":17.4,"effort":4422.864,"length":57,"time":245.715,"vocabulary":22,"volume":254.188,"operands":{"distinct":10,"total":29,"identifiers":["__stripped__"]},"operators":{"distinct":12,"total":28,"identifiers":["__stripped__"]}},"params":2,"sloc":{"logical":9,"physical":12},"errors":[],"lineEnd":88,"lineStart":77,"name":"<anonymous>"}],"methodAverage":{"cyclomatic":1.615,"cyclomaticDensity":92.973,"halstead":{"bugs":0.019,"difficulty":3.831,"effort":464.319,"length":16.038,"time":25.795,"vocabulary":9.615,"volume":57.535,"operands":{"distinct":5.192,"total":8.5},"operators":{"distinct":4.423,"total":7.538}},"params":0.923,"sloc":{"logical":2.077,"physical":3.346}},"module":"lib/util/set.js"},"jshint":{"messages":[]}}